x11_hash.cp36-win32.pyd
x11_hashw-1.7.dist-info/LICENSE
x11_hashw-1.7.dist-info/METADATA
x11_hashw-1.7.dist-info/WHEEL
x11_hashw-1.7.dist-info/top_level.txt
x11_hashw-1.7.dist-info/RECORD
