Metadata-Version: 2.1
Name: x11-hashw
Version: 1.7
Summary: Binding for X11 proof of work hashing.
Home-page: https://github.com/mazaclub/x11_hash
Maintainer: mazaclub
Maintainer-email: kefkius@maza.club
License: UNKNOWN
Platform: UNKNOWN
